purse/__init__.py
purse/__main__.py
purse/accessory.py
purse/main.py
purse/package.py
purse_py-0.0.1a0.dist-info/licenses/LICENSE
purse_py-0.0.1a0.dist-info/METADATA
purse_py-0.0.1a0.dist-info/WHEEL
purse_py-0.0.1a0.dist-info/entry_points.txt
purse_py-0.0.1a0.dist-info/top_level.txt
purse_py-0.0.1a0.dist-info/RECORD
