Metadata-Version: 2.4
Name: purse-py
Version: 0.0.1a0
Summary: Purse: Personalize your Wallet
Author: ApeWorX LTD
Requires-Python: >=3.10
License-File: LICENSE
Requires-Dist: eth-ape>=0.8.32
Requires-Dist: snekmate>=0.0.1
Dynamic: license-file
